Workbook

Sheet FS Data
A1: Accenture
F3: =E4 -> 2024 | G3: =F3+1 -> 2025 | M3: =F3 -> 2024 | N3: =G3 -> 2025
A4: INCOME STATEMENT | B4: 2021 | C4: =B4+1 -> 2022 | D4: =C4+1 -> 2023 | E4: =D4+1 -> 2024 | F4: Optimized | G4: Forecast | I4: =B4 -> 2021 | J4: =C4 -> 2022 | K4: =D4 -> 2023 | L4: =E4 -> 2024 | M4: Optimized | N4: Forecast
A5: Sales | B5: 50533.389 | C5: 61594.305 | D5: 64111.745 | E5: 64896.464 | F5: =E5 -> 64896.464 | G5: =F5*N5 -> 68790.252 | I5: =B5/$B$5 -> 1 | J5: =C5/$C$5 -> 1 | K5: =D5/$D$5 -> 1 | L5: =E5/$E$5 -> 1 | M5: =F5/$E$5 -> 1 | N5: 1.06
A6: Cost of Sales | B6: 34169.233 | C6: 41892.766 | D6: 43380.138 | E6: 43734.147 | F6: =E6 -> 43734.147 | G6: =G5*N6 -> 46777.371 | I6: =B6/$B$5 -> 0.67617141 | J6: =C6/$C$5 -> 0.68014025 | K6: =D6/$D$5 -> 0.67663324 | L6: =E6/$E$5 -> 0.67390647 | M6: =F6/$E$5 -> 0.67390647 | N6: 0.68
A7: Gross Operating Profit | B7: =B5-B6 -> 16364.156 | C7: =C5-C6 -> 19701.539 | D7: =D5-D6 -> 20731.607 | E7: =E5-E6 -> 21162.317 | F7: =F5-F6 -> 21162.317 | G7: =G5-G6 -> 22012.881 | I7: =B7/$B$5 -> 0.32382859 | J7: =C7/$C$5 -> 0.31985975 | K7: =D7/$D$5 -> 0.32336676 | L7: =E7/$E$5 -> 0.32609353 | M7: =F7/$F$5 -> 0.32609353 | N7: =G7/$F$5 -> 0.3392
A9: Selling, General & Admin. Expense | B9: 8742.599 | C9: 10334.358 | D9: 11921.718 | E9: 11566.47 | F9: =E9 -> 11566.47 | G9: =G5*N9 -> 11763.133 | I9: =B9/$B$5 -> 0.17300639 | J9: =C9/$C$5 -> 0.16778106 | K9: =D9/$D$5 -> 0.18595217 | L9: =E9/$E$5 -> 0.17822959 | M9: =F9/$E$5 -> 0.17822959 | N9: 0.171
A10: EBITDA | B10: =B7-B9 -> 7621.557 | C10: =C7-C9 -> 9367.181 | D10: =D7-D9 -> 8809.889 | E10: =E7-E9 -> 9595.847 | F10: =F7-F9 -> 9595.847 | G10: =G7-G9 -> 10249.748 | I10: =B10/$B$5 -> 0.1508222 | J10: =C10/$C$5 -> 0.15207869 | K10: =D10/$D$5 -> 0.13741459 | L10: =E10/$E$5 -> 0.14786394 | M10: =F10/$F$5 -> 0.14786394 | N10: =G10/$F$5 -> 0.15794
A12: Depreciation & Amortization | B12: 1121.973 | C12: 1310.738 | D12: 1400.755 | E12: 1430.042 | F12: =E12/E5*F5 -> 1430.042 | G12: =F12/F5*G5 -> 1515.8445 | I12: =B12/$B$5 -> 0.022202607 | J12: =C12/$C$5 -> 0.021280182 | K12: =D12/$D$5 -> 0.021848649 | L12: =E12/$E$5 -> 0.022035746 | M12: =F12/$F$5 -> 0.022035746 | N12: =G12/$F$5 -> 0.023357891
A13: EBIT | B13: =B10-B12 -> 6499.584 | C13: =C10-C12 -> 8056.443 | D13: =D10-D12 -> 7409.134 | E13: =E10-E12 -> 8165.805 | F13: =F10-F12 -> 8165.805 | G13: =G10-G12 -> 8733.903 | I13: =B13/$B$5 -> 0.12861959 | J13: =C13/$C$5 -> 0.1307985 | K13: =D13/$D$5 -> 0.11556594 | L13: =E13/$E$5 -> 0.1258282 | M13: =F13/$F$5 -> 0.1258282 | N13: =G13/$F$5 -> 0.13458211
A15: Interest Expense | B15: 58.969 | C15: 47.525 | D15: 47.32 | E15: 59.492 | F15: =E15/(E45+E50)*(F45+F50) -> 59.492 | G15: =F15/(F45+F50)*(G45+G50) -> 62.787663 | I15: =B15/$B$5 -> 0.0011669314 | J15: =C15/$C$5 -> 0.00077158107 | K15: =D15/$D$5 -> 0.00073808629 | L15: =E15/$E$5 -> 0.00091672175 | M15: =F15/$F$5 -> 0.00091672175 | N15: =G15/$F$5 -> 0.00096750515
A16: Pre-tax Income (EBT) | B16: =B13-B15 -> 6440.615 | C16: =C13-C15 -> 8008.918 | D16: =D13-D15 -> 7361.814 | E16: =E13-E15 -> 8106.313 | F16: =F13-F15 -> 8106.313 | G16: =G13-G15 -> 8671.1153 | I16: =B16/$B$5 -> 0.12745266 | J16: =C16/$C$5 -> 0.13002692 | K16: =D16/$D$5 -> 0.11482785 | L16: =E16/$E$5 -> 0.12491147 | M16: =F16/$F$5 -> 0.12491147 | N16: =G16/$F$5 -> 0.1336146
A18: Income Taxes | B18: 1770.571 | C18: 2207.207 | D18: 2135.82 | E18: 2280.126 | F18: =E18/E16*F16 -> 2280.126 | G18: =F18/F16*G16 -> 2438.9924 | I18: =B18/$B$5 -> 0.035037646 | J18: =C18/$C$5 -> 0.035834595 | K18: =D18/$D$5 -> 0.033314021 | L18: =E18/$E$5 -> 0.035134826 | M18: =F18/$F$5 -> 0.035134826 | N18: =G18/$F$5 -> 0.037582824
A19: Net Income from Cont. Operations | B19: =B16-B18 -> 4670.044 | C19: =C16-C18 -> 5801.711 | D19: =D16-D18 -> 5225.994 | E19: =E16-E18 -> 5826.187 | F19: =F16-F18 -> 5826.187 | G19: =G16-G18 -> 6232.123 | I19: =B19/$B$5 -> 0.092415017 | J19: =C19/$C$5 -> 0.094192328 | K19: =D19/$D$5 -> 0.081513832 | L19: =E19/$E$5 -> 0.089776648 | M19: =F19/$F$5 -> 0.089776648 | N19: =G19/$F$5 -> 0.09603178
A21: Net Income from Other Items | B21: 5906.809 | C21: 6877.169 | D21: 6871.557 | E21: 7264.787 | F21: 0 | G21: 0 | I21: =B21/$B$5 -> 0.11688923 | J21: =C21/$C$5 -> 0.11165268 | K21: =D21/$D$5 -> 0.10718094 | L21: =E21/$E$5 -> 0.11194427 | M21: =F21/$F$5 -> 0 | N21: =G21/$F$5 -> 0
A22: Total Net Income | B22: =B19+B21 -> 10576.853 | C22: =C19+C21 -> 12678.88 | D22: =D19+D21 -> 12097.551 | E22: =E19+E21 -> 13090.974 | F22: =F19+F21 -> 5826.187 | G22: =G19+G21 -> 6232.123 | I22: =B22/$B$5 -> 0.20930425 | J22: =C22/$C$5 -> 0.205845 | K22: =D22/$D$5 -> 0.18869477 | L22: =E22/$E$5 -> 0.20172091 | M22: =F22/$F$5 -> 0.089776648 | N22: =G22/$F$5 -> 0.09603178
C23: =(C22-B22)/B22 -> 0.19873841 | D23: =(D22-C22)/C22 -> -0.045850186 | E23: =(E22-D22)/D22 -> 0.082117695 | F23: =(F22-E22)/E22 -> -0.55494626 | G23: =(G22-F22)/F22 -> 0.069674381
A25: BALANCE SHEET | B25: =B4 -> 2021 | C25: =C4 -> 2022 | D25: =D4 -> 2023 | E25: =E4 -> 2024 | F25: Optimized | G25: Forecast | I25: =B25 -> 2021 | J25: =C25 -> 2022 | K25: =D25 -> 2023 | L25: =E25 -> 2024 | M25: Optimized | N25: Forecast
A26: Assets
A27: Current Assets
A28: Cash and Equivalents | B28: 8168.174 | C28: 7893.806 | D28: 9049.607 | E28: 5009.865 | F28: =E28/$E$5*F5 -> 5009.865 | G28: =F28/$F$5*G5 -> 5310.4569 | I28: =B28/$B$40 -> 0.22321359 | J28: =C28/$C$40 -> 0.1925708 | K28: =D28/$D$40 -> 0.20901456 | L28: =E28/$E$40 -> 0.10500571 | M28: =F28/$F$40 -> 0.096557694 | N28: =G28/$F$40 -> 0.10235116
A29: Accounts Receivable | B29: 9728.212 | C29: 11776.775 | D29: 12227.186 | E29: 13664.847 | F29: =F5*Ratios!F20/365 -> 13512.688 | G29: =G5*Ratios!G20/365 -> 14323.45 | I29: =B29/$B$40 -> 0.26584512 | J29: =C29/$C$40 -> 0.28729653 | K29: =D29/$D$40 -> 0.28240562 | L29: =E29/$E$40 -> 0.28641229 | M29: =F29/$F$40 -> 0.26043696 | N29: =G29/$F$40 -> 0.27606318
A30: Inventories | B30: 0 | C30: 0 | D30: 0 | E30: 0 | F30: =F5/Ratios!F21 -> 4326.4309 | G30: =G5/Ratios!G21 -> 4586.0168 | I30: =B30/$B$40 -> 0 | J30: =C30/$C$40 -> 0 | K30: =D30/$D$40 -> 0 | L30: =E30/$E$40 -> 0 | M30: =F30/$F$40 -> 0.083385519 | N30: =G30/$F$40 -> 0.088388651
A31: Other Current Assets | B31: 1765.831 | C31: 1940.29 | D31: 2105.138 | E31: 2183.069 | F31: =E31/$E$5*F5 -> 2183.069 | G31: =F31/$F$5*G5 -> 2314.0531 | I31: =B31/$B$40 -> 0.048255275 | J31: =C31/$C$40 -> 0.04733372 | K31: =D31/$D$40 -> 0.048621392 | L31: =E31/$E$40 -> 0.045756663 | M31: =F31/$F$40 -> 0.042075407 | N31: =G31/$F$40 -> 0.044599931
A32: Total Current Assets | B32: =SUM(B28:B31) -> 19662.217 | C32: =SUM(C28:C31) -> 21610.871 | D32: =SUM(D28:D31) -> 23381.931 | E32: =SUM(E28:E31) -> 20857.781 | F32: =SUM(F28:F31) -> 25032.053 | G32: =SUM(G28:G31) -> 26533.977 | I32: =B32/$B$40 -> 0.53731398 | J32: =C32/$C$40 -> 0.52720105 | K32: =D32/$D$40 -> 0.54004157 | L32: =E32/$E$40 -> 0.43717466 | M32: =F32/$F$40 -> 0.48245559 | N32: =G32/$F$40 -> 0.51140292
A34: Long Term Assets
A35: Property, Plant & Equipment, Net | B35: 1639.105 | C35: 1649.14 | D35: 1530.007 | E35: 1521.119 | F35: =E35/$E$5*F5-(F12-E12) -> 1521.119 | G35: =F35/$F$5*G5-(G12-F12) -> 1526.5836 | I35: =B35/$B$40 -> 0.044792204 | J35: =C35/$C$40 -> 0.040231064 | K35: =D35/$D$40 -> 0.035337859 | L35: =E35/$E$40 -> 0.031882331 | M35: =F35/$F$40 -> 0.029317306 | N35: =G35/$F$40 -> 0.029422628
A36: Intangibles/Goodwill | B36: 12836.799 | C36: 15064.101 | D36: 17645.96 | E36: 24024.21 | F36: =E36/$E$5*F5 -> 24024.21 | G36: =F36/$F$5*G5 -> 25465.663 | I36: =B36/$B$40 -> 0.3507942 | J36: =C36/$C$40 -> 0.36749143 | K36: =D36/$D$40 -> 0.40756052 | L36: =E36/$E$40 -> 0.50354234 | M36: =F36/$F$40 -> 0.4630309 | N36: =G36/$F$40 -> 0.49081276
A37: Other Non-Current Assets | B37: 2455.412 | C37: 2667.595 | D37: 738.641 | E37: 1307.297 | F37: =E37 -> 1307.297 | G37: =F37 -> 1307.297 | I37: =B37/$B$40 -> 0.067099616 | J37: =C37/$C$40 -> 0.065076456 | K37: =D37/$D$40 -> 0.017060047 | L37: =E37/$E$40 -> 0.027400668 | M37: =F37/$F$40 -> 0.025196205 | N37: =G37/$F$40 -> 0.025196205
A38: Total Non-Current Assets | B38: =SUM(B35:B37) -> 16931.316 | C38: =SUM(C35:C37) -> 19380.836 | D38: =SUM(D35:D37) -> 19914.608 | E38: =SUM(E35:E37) -> 26852.626 | F38: =SUM(F35:F37) -> 26852.626 | G38: =SUM(G35:G37) -> 28299.543 | I38: =B38/$B$40 -> 0.46268602 | J38: =C38/$C$40 -> 0.47279895 | K38: =D38/$D$40 -> 0.45995843 | L38: =E38/$E$40 -> 0.56282534 | M38: =F38/$F$40 -> 0.51754441 | N38: =G38/$F$40 -> 0.54543159
A40: Total Assets | B40: =B32+B38 -> 36593.533 | C40: =C32+C38 -> 40991.707 | D40: =D32+D38 -> 43296.539 | E40: =E32+E38 -> 47710.407 | F40: =F32+F38 -> 51884.679 | G40: =G32+G38 -> 54833.52 | I40: =B40/$B$40 -> 1 | J40: =C40/$C$40 -> 1 | K40: =D40/$D$40 -> 1 | L40: =E40/$E$40 -> 1 | M40: =F40/$F$40 -> 1 | N40: =G40/$F$40 -> 1.0568345
A42: Liabilities
A43: Current Liabilities
A44: Accounts Payable | B44: 10723.446 | C44: 12328.675 | D44: 12306.659 | E44: 12128.773 | F44: =(F6+F30-D30)/Ratios!F24 -> 25295.041 | G44: =(G6+G30-F30)/Ratios!G24 -> 24756.293 | I44: =B44/$B$60 -> 0.32533025 | J44: =C44/$C$60 -> 0.32944488 | K44: =D44/$D$60 -> 0.29477046 | L44: =E44/$E$60 -> 0.26771396 | M44: =F44/$F$60 -> 0.48752428 | N44: =G44/$F$60 -> 0.47714072
A45: Short Term Debt | B45: 12.08 | C45: 9.175 | D45: 104.81 | E45: 946.229 | F45: =E45/$E$5*F5 -> 946.229 | G45: =F45/$F$5*G5 -> 1003.0027 | I45: =B45/$B$60 -> 0.00036648569 | J45: =C45/$C$60 -> 0.00024517288 | K45: =D45/$D$60 -> 0.0025104207 | L45: =E45/$E$60 -> 0.020885766 | M45: =F45/$F$60 -> 0.018237156 | N45: =G45/$F$60 -> 0.019331386
A46: Other Current Liabilities | B46: 1278.136 | C46: 1510.925 | D46: 1588.678 | E46: 1615.049 | F46: =E46/$E$5*F5 -> 1615.049 | G46: =F46/$F$5*G5 -> 1711.9519 | I46: =B46/$B$60 -> 0.03877637 | J46: =C46/$C$60 -> 0.040374696 | K46: =D46/$D$60 -> 0.038052191 | L46: =E46/$E$60 -> 0.035648385 | M46: =F46/$F$60 -> 0.031127667 | N46: =G46/$F$60 -> 0.032995327
A47: Total Current Liabilities | B47: =SUM(B44:B46) -> 12013.662 | C47: =SUM(C44:C46) -> 13848.775 | D47: =SUM(D44:D46) -> 14000.147 | E47: =SUM(E44:E46) -> 14690.051 | F47: =SUM(F44:F46) -> 27856.319 | G47: =SUM(G44:G46) -> 27471.248 | I47: =B47/$B$60 -> 0.36447311 | J47: =C47/$C$60 -> 0.37006475 | K47: =D47/$D$60 -> 0.33533307 | L47: =E47/$E$60 -> 0.32424811 | M47: =F47/$F$60 -> 0.5368891 | N47: =G47/$F$60 -> 0.52946743
A49: Long Term Liabilities
A50: Long Term Debt | B50: 53.473 | C50: 45.893 | D50: 430.93 | E50: 78.628 | F50: =E50 -> 78.628 | G50: =F50 -> 78.628 | I50: =B50/$B$60 -> 0.0016222756 | J50: =C50/$C$60 -> 0.0012263454 | K50: =D50/$D$60 -> 0.010321683 | L50: =E50/$E$60 -> 0.001735527 | M50: =F50/$F$60 -> 0.0015154377 | N50: =G50/$F$60 -> 0.0015154377
A51: Deferred LT Liabilities | B51: 243.636 | C51: 318.584 | D51: 395.28 | E51: 428.845 | F51: =E51 -> 428.845 | G51: =F51 -> 428.845 | I51: =B51/$B$60 -> 0.0073914823 | J51: =C51/$C$60 -> 0.0085131506 | K51: =D51/$D$60 -> 0.0094677903 | L51: =E51/$E$60 -> 0.0094657385 | M51: =F51/$F$60 -> 0.0082653493 | N51: =G51/$F$60 -> 0.0082653493
A52: Other Non-Current Liabilities | B52: 553.839 | C52: 462.233 | D52: 465.024 | E52: 939.198 | F52: =E52 -> 939.198 | G52: =F52 -> 939.198 | I52: =B52/$B$60 -> 0.016802489 | J52: =C52/$C$60 -> 0.012351716 | K52: =D52/$D$60 -> 0.011138306 | L52: =E52/$E$60 -> 0.020730573 | M52: =F52/$F$60 -> 0.018101644 | N52: =G52/$F$60 -> 0.018101644
A53: Total Non-Current Liabilities | B53: =SUM(B50:B52) -> 850.948 | C53: =SUM(C50:C52) -> 826.71 | D53: =SUM(D50:D52) -> 1291.234 | E53: =SUM(E50:E52) -> 1446.671 | F53: =SUM(F50:F52) -> 1446.671 | G53: =SUM(G50:G52) -> 1446.671 | I53: =B53/$B$60 -> 0.025816247 | J53: =C53/$C$60 -> 0.022091212 | K53: =D53/$D$60 -> 0.03092778 | L53: =E53/$E$60 -> 0.031931839 | M53: =F53/$F$60 -> 0.027882431 | N53: =G53/$F$60 -> 0.027882431
A55: Total Liabilities | B55: =B47+B53 -> 12864.61 | C55: =C47+C53 -> 14675.485 | D55: =D47+D53 -> 15291.381 | E55: =E47+E53 -> 16136.722 | F55: =F47+F53 -> 29302.99 | G55: =G47+G53 -> 28917.919 | I55: =B55/$B$60 -> 0.39028936 | J55: =C55/$C$60 -> 0.39215596 | K55: =D55/$D$60 -> 0.36626085 | L55: =E55/$E$60 -> 0.35617995 | M55: =F55/$F$60 -> 0.56477154 | N55: =G55/$F$60 -> 0.55734986
A57: Stockholders Equity
A58: Total Equity | B58: 20097.114 | C58: 22747.088 | D58: 26458.593 | E58: 29168.248 | F58: =F40-F55 -> 22581.689 | G58: =G40-G55 -> 25915.601 | I58: =B58/$B$60 -> 0.60971064 | J58: =C58/$C$60 -> 0.60784404 | K58: =D58/$D$60 -> 0.63373915 | L58: =E58/$E$60 -> 0.64382005 | M58: =F58/$F$60 -> 0.43522846 | N58: =G58/$F$60 -> 0.49948465
A60: Total Liabilities & Stock Equity | B60: =B55+B58 -> 32961.724 | C60: =C55+C58 -> 37422.573 | D60: =D55+D58 -> 41749.974 | E60: =E55+E58 -> 45304.97 | F60: =F55+F58 -> 51884.679 | G60: =G55+G58 -> 54833.52 | I60: =B60/$B$60 -> 1 | J60: =C60/$C$60 -> 1 | K60: =D60/$D$60 -> 1 | L60: =E60/$E$60 -> 1 | M60: =F60/$F$60 -> 1 | N60: =G60/$F$60 -> 1.0568345
A62: Total Common Shares Outstanding (millions) | B62: 634.745 | C62: 632.76 | D62: 630.608 | E62: 627.85 | F62: =E62 -> 627.85 | G62: =F62 -> 627.85
A63: Total Diluted Shares Outstanding (millions) | B63: 645.909 | C63: 642.839 | D63: 638.591 | E63: 635.94 | F63: =E63 -> 635.94 | G63: =F63 -> 635.94
A64: Stock Price | B64: 412.11 | C64: 254.87 | D64: 340.5 | E64: 351.79 | F64: =F66/F62 -> 156.56546 | G64: =G66/G62 -> 167.47406
A65: Dividends | B65: 3.52 | C65: 3.88 | D65: 4.48 | E65: 4.96 | F65: =E65 -> 4.96 | G65: =F65/F64*G64 -> 5.3055849
A66: Market Cap (millions) | B66: =B62*B64 -> 261584.76 | C66: =C62*C64 -> 161271.54 | D66: =D62*D64 -> 214722.02 | E66: =E62*E64 -> 220871.35 | F66: =E66/E22*F22 -> 98299.622 | G66: =F66/F22*G22 -> 105148.59
A67: Economic Value (millions) | B67: =B66+B53 -> 262435.71 | C67: =C66+C53 -> 162098.25 | D67: =D66+D53 -> 216013.26 | E67: =E66+E53 -> 222318.02 | F67: =F66+F53 -> 99746.293 | G67: =G66+G53 -> 106595.26
A70: STATEMENT OF CASH FLOWS | B70: =B25 -> 2021 | C70: =C25 -> 2022 | D70: =D25 -> 2023 | E70: =E25 -> 2024 | F70: Optimized | G70: Forecast
A72: Cash Flows From Operating Activities
A73: Net Income (Loss) | B73: =B22 -> 10576.853 | C73: =C22 -> 12678.88 | D73: =D22 -> 12097.551 | E73: =E22 -> 13090.974 | F73: =F22 -> 5826.187 | G73: =G22 -> 6232.123
A74: Depreciation and Amortization | B74: =B12 -> 1121.973 | C74: =C12 -> 1310.738 | D74: =D12 -> 1400.755 | E74: =E12 -> 1430.042 | F74: =F12 -> 1430.042 | G74: =G12 -> 1515.8445
A75: Other Adjustments to Net Income | B75: 1061.032 | C75: 1270.52 | D75: 1702.682 | E75: 1702.682 | F75: =E75 -> 1702.682 | G75: =F75 -> 1702.682
A76: Changes in Other Operating Activities | B76: -342.849 | C76: -195.975 | D76: -219.082 | E76: -144.92 | F76: =E76 -> -144.92 | G76: =F76 -> -144.92
A77: Change in NC Working Capital
A78: (Increase) Decr. in Receivables | B78: 1471.613 | C78: 2411.735 | D78: 87.669 | E78: -601.935 | F78: =D29-F29+36 -> -1249.5024 | G78: =F29-G29 -> -810.7613
A79: (Increase) Decr. in Inventories | B79: 0 | C79: 0 | D79: 0 | E79: 0 | F79: =D30-F30 -> -4326.4309 | G79: =F30-G30 -> -259.58586
A80: (Decrease) Incr. in Liabilities | B80: 1983.983 | C80: 1848.765 | D80: -860.055 | E80: -328.53 | F80: =F47-D47-782 -> 13074.172 | G80: =G47-F47 -> -385.07112
A81: Net Cash from Operating Activities | B81: =SUM(B73:B76)+SUM(B78:B80) -> 15872.605 | C81: =SUM(C73:C76)+SUM(C78:C80) -> 19324.663 | D81: =SUM(D73:D76)+SUM(D78:D80) -> 14209.52 | E81: =SUM(E73:E76)+SUM(E78:E80) -> 15148.313 | F81: =SUM(F73:F76)+SUM(F78:F80) -> 16312.23 | G81: =SUM(G73:G76)+SUM(G78:G80) -> 7850.3112
A83: Cash Flow from Investing Activities
A84: Capital Expenditures | B84: -580 | C84: -717 | D84: -528 | E84: -863 | F84: =E84+(E12-F12) -> -863 | G84: =F84+(F12-G12) -> -948.80252
A85: Other Investing Cash Flow Items, Total | B85: -3729 | C85: -3327 | D85: -2094 | E85: -6199 | F85: =E85/E5*F5 -> -6199 | G85: =F85/F5*G5 -> -6570.94
A86: Net Cash from Investing Activities | B86: =SUM(B84:B85) -> -4309 | C86: =SUM(C84:C85) -> -4044 | D86: =SUM(D84:D85) -> -2622 | E86: =SUM(E84:E85) -> -7062 | F86: =SUM(F84:F85) -> -7062 | G86: =SUM(G84:G85) -> -7519.7425
A88: Cash Flow from Financing Activities
A89: Total Cash Dividends Paid | B89: -2236 | C89: -2457 | D89: -2827 | E89: -3241 | F89: =-F65*(F62+F63)/2 -> -3134.1992 | G89: =-G65*(G62+G63)/2 -> -3352.5726
A90: Issuance (Retirement) of Stock, Net | B90: -2667 | C90: -2767 | D90: -2829.334 | E90: -2828 | F90: =E90 -> -2828 | G90: =F90 -> -2828
A91: Issuance (Retirement) of Debt, Net | B91: -7.798 | C91: -16 | D91: 93 | E91: 0 | F91: =E91 -> 0 | G91: =F91 -> 0
A92: Other Financing Cash Flows | B92: -45.096 | C92: -69.95 | D92: -81.856 | E92: -543.301 | F92: =E92 -> -543.301 | G92: =F92 -> -543.301
A93: Net Cash from Financing Activities | B93: =SUM(B89:B92) -> -4955.894 | C93: =SUM(C89:C92) -> -5309.95 | D93: =SUM(D89:D92) -> -5645.19 | E93: =SUM(E89:E92) -> -6612.301 | F93: =SUM(F89:F92) -> -6505.5002 | G93: =SUM(G89:G92) -> -6723.8736
A95: Effect of Exchange Rate Changes | B95: 0 | C95: 0 | D95: 0 | E95: 0 | F95: =E95 -> 0 | G95: =F95 -> 0
A96: Net Change in Cash & Cash Equivalents | B96: =B81+B86+B93+B95 -> 6607.711 | C96: =C81+C86+C93+C95 -> 9970.713 | D96: =D81+D86+D93+D95 -> 5942.33 | E96: =E81+E86+E93+E95 -> 1474.012 | F96: =F81+F86+F93+F95 -> 2744.7295 | G96: =G81+G86+G93+G95 -> -6393.3049
A97: Cash at Beginning of Period | B97: =B28-B96 -> 1560.463 | C97: =B98 -> 8168.174 | D97: =C98 -> 18138.887 | E97: =D98 -> 24081.217 | F97: =E97 -> 24081.217 | G97: =F98 -> 26825.946
A98: Cash at End of Period | B98: =B96+B97 -> 8168.174 | C98: =C96+C97 -> 18138.887 | D98: =D96+D97 -> 24081.217 | E98: =E96+E97 -> 25555.229 | F98: =F96+F97 -> 26825.946 | G98: =G96+G97 -> 20432.642

Sheet Ratios
A1: ='FS Data'!A1 -> Accenture
F2: ='FS Data'!F3 -> 2024 | G2: ='FS Data'!G3 -> 2025
A3: ENTERPRISE VALUATION MULTIPLES | B3: ='FS Data'!B4 -> 2021 | C3: ='FS Data'!C4 -> 2022 | D3: ='FS Data'!D4 -> 2023 | E3: ='FS Data'!E4 -> 2024 | F3: Optimized | G3: Forecast
A4: EV/Sales | B4: ='FS Data'!B67/'FS Data'!B5 -> 5.1933131 | C4: ='FS Data'!C67/'FS Data'!C5 -> 2.6317084 | D4: ='FS Data'!D67/'FS Data'!D5 -> 3.3693243 | E4: ='FS Data'!E67/'FS Data'!E5 -> 3.425734 | F4: ='FS Data'!F67/'FS Data'!F5 -> 1.5370066 | G4: ='FS Data'!G67/'FS Data'!G5 -> 1.5495692
A5: EV/EBITDA | B5: ='FS Data'!B67/'FS Data'!B10 -> 34.433346 | C5: ='FS Data'!C67/'FS Data'!C10 -> 17.304913 | D5: ='FS Data'!D67/'FS Data'!D10 -> 24.519407 | E5: ='FS Data'!E67/'FS Data'!E10 -> 23.16815 | F5: ='FS Data'!F67/'FS Data'!F10 -> 10.394736 | G5: ='FS Data'!G67/'FS Data'!G10 -> 10.399794
A6: EV/Operating FCF | B6: ='FS Data'!B67/'FS Data'!B81 -> 16.533878 | C6: ='FS Data'!C67/'FS Data'!C81 -> 8.3881541 | D6: ='FS Data'!D67/'FS Data'!D81 -> 15.202009 | E6: ='FS Data'!E67/'FS Data'!E81 -> 14.676091 | F6: ='FS Data'!F67/'FS Data'!F81 -> 6.1148166 | G6: ='FS Data'!G67/'FS Data'!G81 -> 13.578475
A7: EV/Enterprise FCF | B7: ='FS Data'!B13-'FS Data'!B18+'FS Data'!B12-'FS Data'!B84+'FS Data'!B78+'FS Data'!B79+'FS Data'!B80-'FS Data'!B75-'FS Data'!B76 -> 9168.399 | C7: ='FS Data'!C13-'FS Data'!C18+'FS Data'!C12-'FS Data'!C84+'FS Data'!C78+'FS Data'!C79+'FS Data'!C80-'FS Data'!C75-'FS Data'!C76 -> 11062.929 | D7: ='FS Data'!D13-'FS Data'!D18+'FS Data'!D12-'FS Data'!D84+'FS Data'!D78+'FS Data'!D79+'FS Data'!D80-'FS Data'!D75-'FS Data'!D76 -> 4946.083 | E7: ='FS Data'!E13-'FS Data'!E18+'FS Data'!E12-'FS Data'!E84+'FS Data'!E78+'FS Data'!E79+'FS Data'!E80-'FS Data'!E75-'FS Data'!E76 -> 5690.494 | F7: ='FS Data'!F13-'FS Data'!F18+'FS Data'!F12-'FS Data'!F84+'FS Data'!F78+'FS Data'!F79+'FS Data'!F80-'FS Data'!F75-'FS Data'!F76 -> 14119.198 | G7: ='FS Data'!G13-'FS Data'!G18+'FS Data'!G12-'FS Data'!G84+'FS Data'!G78+'FS Data'!G79+'FS Data'!G80-'FS Data'!G75-'FS Data'!G76 -> 5746.3774
A9: EQUITY VALUATION MULTIPLES
A10: Price/Earnings Ratio | B10: =B44 -> 24.731814 | C10: =C44 -> 12.719699 | D10: =D44 -> 17.749214 | E10: =E44 -> 16.872033 | F10: =F44 -> 16.872033 | G10: =G44 -> 16.872033
A11: Price/Cash Earnings | B11: =B45 -> 22.359916 | C11: =C45 -> 11.527945 | D11: =D45 -> 15.907331 | E11: =E45 -> 15.210461 | F11: =F45 -> 13.546929 | G11: =G45 -> 13.571119
A12: Price/Earnings Growth | B12: -- | C12: =C10/('FS Data'!C22/'FS Data'!B22) -> 10.610905 | D12: =D10/('FS Data'!D22/'FS Data'!C22) -> 18.602125 | E12: =E10/('FS Data'!E22/'FS Data'!D22) -> 15.591681 | F12: =F10/('FS Data'!F22/'FS Data'!E22) -> 37.910103 | G12: =G10/('FS Data'!G22/'FS Data'!F22) -> 15.773056
A14: LIQUIDITY RATIOS
A15: Current Ratio [CA/CL] | B15: ='FS Data'!B32/'FS Data'!B47 -> 1.6366548 | C15: ='FS Data'!C32/'FS Data'!C47 -> 1.5604897 | D15: ='FS Data'!D32/'FS Data'!D47 -> 1.6701204 | E15: ='FS Data'!E32/'FS Data'!E47 -> 1.4198576 | F15: ='FS Data'!F32/'FS Data'!F47 -> 0.89861311 | G15: ='FS Data'!G32/'FS Data'!G47 -> 0.96588173
A16: Quick Ratio [(CA-Inv)/CL] | B16: =('FS Data'!B28+'FS Data'!B31+'FS Data'!B29)/'FS Data'!B47 -> 1.6366548 | C16: =('FS Data'!C28+'FS Data'!C31+'FS Data'!C29)/'FS Data'!C47 -> 1.5604897 | D16: =('FS Data'!D28+'FS Data'!D31+'FS Data'!D29)/'FS Data'!D47 -> 1.6701204 | E16: =('FS Data'!E28+'FS Data'!E31+'FS Data'!E29)/'FS Data'!E47 -> 1.4198576 | F16: =('FS Data'!F28+'FS Data'!F31+'FS Data'!F29)/'FS Data'!F47 -> 0.74330073 | G16: =('FS Data'!G28+'FS Data'!G31+'FS Data'!G29)/'FS Data'!G47 -> 0.79894295
A17: Cash Ratio [(Cash+Cash Eq)/CL] | B17: =('FS Data'!B28+'FS Data'!B31)/'FS Data'!B47 -> 0.82689233 | C17: =('FS Data'!C28+'FS Data'!C31)/'FS Data'!C47 -> 0.71010584 | D17: =('FS Data'!D28+'FS Data'!D31)/'FS Data'!D47 -> 0.79675913 | E17: =('FS Data'!E28+'FS Data'!E31)/'FS Data'!E47 -> 0.48964663 | F17: =('FS Data'!F28+'FS Data'!F31)/'FS Data'!F47 -> 0.25821552 | G17: =('FS Data'!G28+'FS Data'!G31)/'FS Data'!G47 -> 0.27754509
A19: ACTIVITY RATIOS
A20: Days Sales Outstanding (DSO) [Recv's/Rev*365] | B20: =('FS Data'!B29/'FS Data'!B5)*365 -> 70.266362 | C20: =('FS Data'!C29/'FS Data'!C5)*365 -> 69.787667 | D20: =('FS Data'!D29/'FS Data'!D5)*365 -> 69.611627 | E20: =('FS Data'!E29/'FS Data'!E5)*365 -> 76.855792 | F20: 76 | G20: =F20 -> 76 | H20: => Lower
A21: Inventory Turnover [Rev/Inv] | B21: ='FS Data'!B5/'FS Data'!B30 -> #DIV/0! | C21: ='FS Data'!C5/'FS Data'!C30 -> #DIV/0! | D21: ='FS Data'!D5/'FS Data'!D30 -> #DIV/0! | E21: ='FS Data'!E5/'FS Data'!E30 -> #DIV/0! | F21: 15 | G21: =F21 -> 15 | H21: => Higher
A22: Fixed Asset Turnover [Rev/Net FA] | B22: ='FS Data'!B5/'FS Data'!B38 -> 2.9846108 | C22: ='FS Data'!C5/'FS Data'!C38 -> 3.1781036 | D22: ='FS Data'!D5/'FS Data'!D38 -> 3.2193325 | E22: ='FS Data'!E5/'FS Data'!E38 -> 2.4167642 | F22: ='FS Data'!F5/'FS Data'!F38 -> 2.4167642 | G22: ='FS Data'!G5/'FS Data'!G38 -> 2.4307902
A23: Total Asset Turnover [Rev/TA] | B23: ='FS Data'!B5/'FS Data'!B40 -> 1.3809377 | C23: ='FS Data'!C5/'FS Data'!C40 -> 1.5026041 | D23: ='FS Data'!D5/'FS Data'!D40 -> 1.4807591 | E23: ='FS Data'!E5/'FS Data'!E40 -> 1.3602161 | F23: ='FS Data'!F5/'FS Data'!F40 -> 1.2507828 | G23: ='FS Data'!G5/'FS Data'!G40 -> 1.2545292
A24: Payables Turnover [Credit Purchases/Average AP] | B24: -- | C24: =('FS Data'!C6+'FS Data'!C30-'FS Data'!B30)/'FS Data'!C44 -> 3.3979942 | D24: =('FS Data'!D6+'FS Data'!D30-'FS Data'!C30)/'FS Data'!D44 -> 3.5249322 | E24: =('FS Data'!E6+'FS Data'!E30-'FS Data'!D30)/'FS Data'!E44 -> 3.6058179 | F24: 1.9 | G24: =F24 -> 1.9 | H24: => Lower
A26: DEBT MANAGEMENT RATIOS
A27: Total Debt to Total Assets [TDebt/TA] | B27: =('FS Data'!B45+'FS Data'!B50)/'FS Data'!B40 -> 0.0017913821 | C27: =('FS Data'!C45+'FS Data'!C50)/'FS Data'!C40 -> 0.0013433937 | D27: =('FS Data'!D45+'FS Data'!D50)/'FS Data'!D40 -> 0.012373737 | E27: =('FS Data'!E45+'FS Data'!E50)/'FS Data'!E40 -> 0.021480785 | F27: =('FS Data'!F45+'FS Data'!F50)/'FS Data'!F40 -> 0.019752594 | G27: =('FS Data'!G45+'FS Data'!G50)/'FS Data'!G40 -> 0.019725722
A28: Debt-to-Capital Ratio (DTIC) [TDebt/(TiC)] | B28: =('FS Data'!B45+'FS Data'!B50)/('FS Data'!B45+'FS Data'!B50+'FS Data'!B58) -> 0.0032512068 | C28: =('FS Data'!C45+'FS Data'!C50)/('FS Data'!C45+'FS Data'!C50+'FS Data'!C58) -> 0.0024150348 | D28: =('FS Data'!D45+'FS Data'!D50)/('FS Data'!D45+'FS Data'!D50+'FS Data'!D58) -> 0.019846388 | E28: =('FS Data'!E45+'FS Data'!E50)/('FS Data'!E45+'FS Data'!E50+'FS Data'!E58) -> 0.033943412 | F28: =('FS Data'!F45+'FS Data'!F50)/('FS Data'!F45+'FS Data'!F50+'FS Data'!F58) -> 0.043414102 | G28: =('FS Data'!G45+'FS Data'!G50)/('FS Data'!G45+'FS Data'!G50+'FS Data'!G58) -> 0.040064506
A29: Debt-to-Equity Ratio [TL/EQ] | B29: =('FS Data'!B45+'FS Data'!B50)/'FS Data'!B58 -> 0.0032618116 | C29: =('FS Data'!C45+'FS Data'!C50)/'FS Data'!C58 -> 0.0024208813 | D29: =('FS Data'!D45+'FS Data'!D50)/'FS Data'!D58 -> 0.020248242 | E29: =('FS Data'!E45+'FS Data'!E50)/'FS Data'!E58 -> 0.035136049 | F29: =('FS Data'!F45+'FS Data'!F50)/'FS Data'!F58 -> 0.045384426 | G29: =('FS Data'!G45+'FS Data'!G50)/'FS Data'!G58 -> 0.041736665
A30: Market Debt Ratio [TDebt/(TDebt+MCap)] | B30: =('FS Data'!B45+'FS Data'!B50)/('FS Data'!B45+'FS Data'!B50+'FS Data'!B66) -> 0.00025053668 | C30: =('FS Data'!C45+'FS Data'!C50)/('FS Data'!C45+'FS Data'!C50+'FS Data'!C66) -> 0.00034134481 | D30: =('FS Data'!D45+'FS Data'!D50)/('FS Data'!D45+'FS Data'!D50+'FS Data'!D66) -> 0.0024888301 | E30: =('FS Data'!E45+'FS Data'!E50)/('FS Data'!E45+'FS Data'!E50+'FS Data'!E66) -> 0.0046186323 | F30: =('FS Data'!F45+'FS Data'!F50)/('FS Data'!F45+'FS Data'!F50+'FS Data'!F66) -> 0.010318272 | G30: =('FS Data'!G45+'FS Data'!G50)/('FS Data'!G45+'FS Data'!G50+'FS Data'!G66) -> 0.01018195
A31: Liabilities to Assets [TL/TA] | B31: ='FS Data'!B55/'FS Data'!B40 -> 0.35155419 | C31: ='FS Data'!C55/'FS Data'!C40 -> 0.35801107 | D31: ='FS Data'!D55/'FS Data'!D40 -> 0.35317791 | E31: ='FS Data'!E55/'FS Data'!E40 -> 0.33822227 | F31: ='FS Data'!F55/'FS Data'!F40 -> 0.56477154 | G31: ='FS Data'!G55/'FS Data'!G40 -> 0.52737667
A32: Times Interest Earned (TIE) [EBIT/Int] | B32: ='FS Data'!B13/'FS Data'!B15 -> 110.22035 | C32: ='FS Data'!C13/'FS Data'!C15 -> 169.52011 | D32: ='FS Data'!D13/'FS Data'!D15 -> 156.57511 | E32: ='FS Data'!E13/'FS Data'!E15 -> 137.25888 | F32: ='FS Data'!F13/'FS Data'!F15 -> 137.25888 | G32: ='FS Data'!G13/'FS Data'!G15 -> 139.10222
A34: PROFITABILITY RATIOS
A35: Gross Profit Margin [EBITDA/Rev] | B35: ='FS Data'!B7/'FS Data'!B5 -> 0.32382859 | C35: ='FS Data'!C7/'FS Data'!C5 -> 0.31985975 | D35: ='FS Data'!D7/'FS Data'!D5 -> 0.32336676 | E35: ='FS Data'!E7/'FS Data'!E5 -> 0.32609353 | F35: ='FS Data'!F7/'FS Data'!F5 -> 0.32609353 | G35: ='FS Data'!G7/'FS Data'!G5 -> 0.32
A36: Operating Profit Margin [EBIT/Rev] | B36: ='FS Data'!B13/'FS Data'!B5 -> 0.12861959 | C36: ='FS Data'!C13/'FS Data'!C5 -> 0.1307985 | D36: ='FS Data'!D13/'FS Data'!D5 -> 0.11556594 | E36: ='FS Data'!E13/'FS Data'!E5 -> 0.1258282 | F36: ='FS Data'!F13/'FS Data'!F5 -> 0.1258282 | G36: ='FS Data'!G13/'FS Data'!G5 -> 0.12696425
A37: Net Profit Margin (NPM) [NI/Rev] | B37: ='FS Data'!B22/'FS Data'!B5 -> 0.20930425 | C37: ='FS Data'!C22/'FS Data'!C5 -> 0.205845 | D37: ='FS Data'!D22/'FS Data'!D5 -> 0.18869477 | E37: ='FS Data'!E22/'FS Data'!E5 -> 0.20172091 | F37: ='FS Data'!F22/'FS Data'!F5 -> 0.089776648 | G37: ='FS Data'!G22/'FS Data'!G5 -> 0.090596019
A38: Basic Earnings Power [EBIT/TA] | B38: ='FS Data'!B13/'FS Data'!B40 -> 0.17761565 | C38: ='FS Data'!C13/'FS Data'!C40 -> 0.19653836 | D38: ='FS Data'!D13/'FS Data'!D40 -> 0.17112532 | E38: ='FS Data'!E13/'FS Data'!E40 -> 0.17115354 | F38: ='FS Data'!F13/'FS Data'!F40 -> 0.15738374 | G38: ='FS Data'!G13/'FS Data'!G40 -> 0.15928036
A39: Return on Invested Capital (ROIC) [EBIT(1-Tax)/TiC] | B39: =('FS Data'!B13*(1-('FS Data'!B18/'FS Data'!B16)))/('FS Data'!B45+'FS Data'!B50+'FS Data'!B58) -> 0.23373902 | C39: =('FS Data'!C13*(1-('FS Data'!C18/'FS Data'!C16)))/('FS Data'!C45+'FS Data'!C50+'FS Data'!C58) -> 0.25594678 | D39: =('FS Data'!D13*(1-('FS Data'!D18/'FS Data'!D16)))/('FS Data'!D45+'FS Data'!D50+'FS Data'!D58) -> 0.19484036 | E39: =('FS Data'!E13*(1-('FS Data'!E18/'FS Data'!E16)))/('FS Data'!E45+'FS Data'!E50+'FS Data'!E58) -> 0.19438031 | F39: =('FS Data'!F13*(1-('FS Data'!F18/'FS Data'!F16)))/('FS Data'!F45+'FS Data'!F50+'FS Data'!F58) -> 0.24861516 | G39: =('FS Data'!G13*(1-('FS Data'!G18/'FS Data'!G16)))/('FS Data'!G45+'FS Data'!G50+'FS Data'!G58) -> 0.23251458
A40: Return on Assets (ROA) [NI/TA] | B40: ='FS Data'!B22/'FS Data'!B40 -> 0.28903613 | C40: ='FS Data'!C22/'FS Data'!C40 -> 0.30930354 | D40: ='FS Data'!D22/'FS Data'!D40 -> 0.2794115 | E40: ='FS Data'!E22/'FS Data'!E40 -> 0.27438404 | F40: ='FS Data'!F22/'FS Data'!F40 -> 0.11229109 | G40: ='FS Data'!G22/'FS Data'!G40 -> 0.11365535
A41: Return on Equity (ROE) [NI/TEQ] | B41: ='FS Data'!B22/'FS Data'!B58 -> 0.52628716 | C41: ='FS Data'!C22/'FS Data'!C58 -> 0.55738475 | D41: ='FS Data'!D22/'FS Data'!D58 -> 0.45722579 | E41: ='FS Data'!E22/'FS Data'!E58 -> 0.44880906 | F41: ='FS Data'!F22/'FS Data'!F58 -> 0.25800492 | G41: ='FS Data'!G22/'FS Data'!G58 -> 0.24047766
A43: PRICE RATIOS
A44: PE Ratio [Price/EPS] | B44: ='FS Data'!B66/'FS Data'!B22 -> 24.731814 | C44: ='FS Data'!C66/'FS Data'!C22 -> 12.719699 | D44: ='FS Data'!D66/'FS Data'!D22 -> 17.749214 | E44: ='FS Data'!E66/'FS Data'!E22 -> 16.872033 | F44: ='FS Data'!F66/'FS Data'!F22 -> 16.872033 | G44: ='FS Data'!G66/'FS Data'!G22 -> 16.872033
A45: P/CF Ratio [Price/(NI+D&A)] | B45: ='FS Data'!B66/('FS Data'!B22+'FS Data'!B12) -> 22.359916 | C45: ='FS Data'!C66/('FS Data'!C22+'FS Data'!C12) -> 11.527945 | D45: ='FS Data'!D66/('FS Data'!D22+'FS Data'!D12) -> 15.907331 | E45: ='FS Data'!E66/('FS Data'!E22+'FS Data'!E12) -> 15.210461 | F45: ='FS Data'!F66/('FS Data'!F22+'FS Data'!F12) -> 13.546929 | G45: ='FS Data'!G66/('FS Data'!G22+'FS Data'!G12) -> 13.571119
A46: Market/Book Ratio [MCap/TEQ or Price/(BV/Share)] | B46: ='FS Data'!B66/'FS Data'!B58 -> 13.016036 | C46: ='FS Data'!C66/'FS Data'!C58 -> 7.0897664 | D46: ='FS Data'!D66/'FS Data'!D58 -> 8.1153984 | E46: ='FS Data'!E66/'FS Data'!E58 -> 7.5723215 | F46: ='FS Data'!F66/'FS Data'!F58 -> 4.3530677 | G46: ='FS Data'!G66/'FS Data'!G58 -> 4.0573471
A48: DUPONT ANALYSIS
A49: Dupont System ROE
A50: ROE = Net Profit / Equity | B50: ='FS Data'!B22/'FS Data'!B58 -> 0.52628716 | C50: ='FS Data'!C22/'FS Data'!C58 -> 0.55738475 | D50: ='FS Data'!D22/'FS Data'!D58 -> 0.45722579 | E50: ='FS Data'!E22/'FS Data'!E58 -> 0.44880906 | F50: ='FS Data'!F22/'FS Data'!F58 -> 0.25800492 | G50: ='FS Data'!G22/'FS Data'!G58 -> 0.24047766
A52: DuPont ROE
A53: ROA = Net Profit / Total Assets | B53: ='FS Data'!B22/'FS Data'!B40 -> 0.28903613 | C53: ='FS Data'!C22/'FS Data'!C40 -> 0.30930354 | D53: ='FS Data'!D22/'FS Data'!D40 -> 0.2794115 | E53: ='FS Data'!E22/'FS Data'!E40 -> 0.27438404 | F53: ='FS Data'!F22/'FS Data'!F40 -> 0.11229109 | G53: ='FS Data'!G22/'FS Data'!G40 -> 0.11365535
A54: Equity Multiplier (EM) = Total Assets / Equity | B54: ='FS Data'!B40/'FS Data'!B58 -> 1.8208352 | C54: ='FS Data'!C40/'FS Data'!C58 -> 1.8020639 | D54: ='FS Data'!D40/'FS Data'!D58 -> 1.6363886 | E54: ='FS Data'!E40/'FS Data'!E58 -> 1.6356967 | F54: ='FS Data'!F40/'FS Data'!F58 -> 2.2976438 | G54: ='FS Data'!G40/'FS Data'!G58 -> 2.1158498
A55: DuPont ROE = ROA * EM | B55: =B53*B54 -> 0.52628716 | C55: =C53*C54 -> 0.55738475 | D55: =D53*D54 -> 0.45722579 | E55: =E53*E54 -> 0.44880906 | F55: =F53*F54 -> 0.25800492 | G55: =G53*G54 -> 0.24047766
A57: Dupont System ROA
A58: ROA = Net Profit / Total Assets | B58: ='FS Data'!B22/'FS Data'!B40 -> 0.28903613 | C58: ='FS Data'!C22/'FS Data'!C40 -> 0.30930354 | D58: ='FS Data'!D22/'FS Data'!D40 -> 0.2794115 | E58: ='FS Data'!E22/'FS Data'!E40 -> 0.27438404 | F58: ='FS Data'!F22/'FS Data'!F40 -> 0.11229109 | G58: ='FS Data'!G22/'FS Data'!G40 -> 0.11365535
A60: DuPont ROA
A61: Net Profit Margin (NPM) = Net Profit / Revenue | B61: ='FS Data'!B22/'FS Data'!B5 -> 0.20930425 | C61: ='FS Data'!C22/'FS Data'!C5 -> 0.205845 | D61: ='FS Data'!D22/'FS Data'!D5 -> 0.18869477 | E61: ='FS Data'!E22/'FS Data'!E5 -> 0.20172091 | F61: ='FS Data'!F22/'FS Data'!F5 -> 0.089776648 | G61: ='FS Data'!G22/'FS Data'!G5 -> 0.090596019
A62: Asset Turnover (ATO) = Revenue / Total Assets | B62: ='FS Data'!B5/'FS Data'!B40 -> 1.3809377 | C62: ='FS Data'!C5/'FS Data'!C40 -> 1.5026041 | D62: ='FS Data'!D5/'FS Data'!D40 -> 1.4807591 | E62: ='FS Data'!E5/'FS Data'!E40 -> 1.3602161 | F62: ='FS Data'!F5/'FS Data'!F40 -> 1.2507828 | G62: ='FS Data'!G5/'FS Data'!G40 -> 1.2545292
A63: DuPont ROA = NPM * ATO | B63: =B61*B62 -> 0.28903613 | C63: =C61*C62 -> 0.30930354 | D63: =D61*D62 -> 0.2794115 | E63: =E61*E62 -> 0.27438404 | F63: =F61*F62 -> 0.11229109 | G63: =G61*G62 -> 0.11365535
A65: DuPont Analysis: 2-Way Approach
A66: Net Profit Margin (NPM) = Net Profit / Revenue | B66: ='FS Data'!B22/'FS Data'!B5 -> 0.20930425 | C66: ='FS Data'!C22/'FS Data'!C5 -> 0.205845 | D66: ='FS Data'!D22/'FS Data'!D5 -> 0.18869477 | E66: ='FS Data'!E22/'FS Data'!E5 -> 0.20172091 | F66: ='FS Data'!F22/'FS Data'!F5 -> 0.089776648 | G66: ='FS Data'!G22/'FS Data'!G5 -> 0.090596019
A67: Equity Turnover (EQTO) = Revenue / Equity | B67: ='FS Data'!B5/'FS Data'!B58 -> 2.51446 | C67: ='FS Data'!C5/'FS Data'!C58 -> 2.7077886 | D67: ='FS Data'!D5/'FS Data'!D58 -> 2.4230973 | E67: ='FS Data'!E5/'FS Data'!E58 -> 2.224901 | F67: ='FS Data'!F5/'FS Data'!F58 -> 2.8738534 | G67: ='FS Data'!G5/'FS Data'!G58 -> 2.6543954
A68: DuPont ROE = NPM * EQTO | B68: =B66*B67 -> 0.52628716 | C68: =C66*C67 -> 0.55738475 | D68: =D66*D67 -> 0.45722579 | E68: =E66*E67 -> 0.44880906 | F68: =F66*F67 -> 0.25800492 | G68: =G66*G67 -> 0.24047766
A70: DuPont Analysis: 3-Way Approach
A71: Net Profit Margin (NPM) = Net Profit / Revenue | B71: ='FS Data'!B22/'FS Data'!B5 -> 0.20930425 | C71: ='FS Data'!C22/'FS Data'!C5 -> 0.205845 | D71: ='FS Data'!D22/'FS Data'!D5 -> 0.18869477 | E71: ='FS Data'!E22/'FS Data'!E5 -> 0.20172091 | F71: ='FS Data'!F22/'FS Data'!F5 -> 0.089776648 | G71: ='FS Data'!G22/'FS Data'!G5 -> 0.090596019
A72: Asset Turnover (ATO) = Revenue / Total Assets | B72: ='FS Data'!B5/'FS Data'!B40 -> 1.3809377 | C72: ='FS Data'!C5/'FS Data'!C40 -> 1.5026041 | D72: ='FS Data'!D5/'FS Data'!D40 -> 1.4807591 | E72: ='FS Data'!E5/'FS Data'!E40 -> 1.3602161 | F72: ='FS Data'!F5/'FS Data'!F40 -> 1.2507828 | G72: ='FS Data'!G5/'FS Data'!G40 -> 1.2545292
A73: Equity Multiplier (EM) = Total Assets / Equity | B73: ='FS Data'!B40/'FS Data'!B58 -> 1.8208352 | C73: ='FS Data'!C40/'FS Data'!C58 -> 1.8020639 | D73: ='FS Data'!D40/'FS Data'!D58 -> 1.6363886 | E73: ='FS Data'!E40/'FS Data'!E58 -> 1.6356967 | F73: ='FS Data'!F40/'FS Data'!F58 -> 2.2976438 | G73: ='FS Data'!G40/'FS Data'!G58 -> 2.1158498
A74: DuPont ROE = NPM * ATO * EM | B74: =B71*B72*B73 -> 0.52628716 | C74: =C71*C72*C73 -> 0.55738475 | D74: =D71*D72*D73 -> 0.45722579 | E74: =E71*E72*E73 -> 0.44880906 | F74: =F71*F72*F73 -> 0.25800492 | G74: =G71*G72*G73 -> 0.24047766
A76: DuPont Analysis: 5-Way Approach
A77: Tax Burden (TB) = Net Profit / EBT | B77: ='FS Data'!B22/'FS Data'!B16 -> 1.6422117 | C77: ='FS Data'!C22/'FS Data'!C16 -> 1.5830952 | D77: ='FS Data'!D22/'FS Data'!D16 -> 1.643284 | E77: ='FS Data'!E22/'FS Data'!E16 -> 1.614911 | F77: ='FS Data'!F22/'FS Data'!F16 -> 0.71872219 | G77: ='FS Data'!G22/'FS Data'!G16 -> 0.71872219
A78: Interest Burden (IB) = EBT / EBIT | B78: ='FS Data'!B16/'FS Data'!B13 -> 0.99092727 | C78: ='FS Data'!C16/'FS Data'!C13 -> 0.99410099 | D78: ='FS Data'!D16/'FS Data'!D13 -> 0.99361329 | E78: ='FS Data'!E16/'FS Data'!E13 -> 0.9927145 | F78: ='FS Data'!F16/'FS Data'!F13 -> 0.9927145 | G78: ='FS Data'!G16/'FS Data'!G13 -> 0.99281104
A79: Operating Profit Margin (OPM) = EBIT / Revenue | B79: ='FS Data'!B13/'FS Data'!B5 -> 0.12861959 | C79: ='FS Data'!C13/'FS Data'!C5 -> 0.1307985 | D79: ='FS Data'!D13/'FS Data'!D5 -> 0.11556594 | E79: ='FS Data'!E13/'FS Data'!E5 -> 0.1258282 | F79: ='FS Data'!F13/'FS Data'!F5 -> 0.1258282 | G79: ='FS Data'!G13/'FS Data'!G5 -> 0.12696425
A80: Asset Turnover (ATO) = Revenue / Total Assets | B80: ='FS Data'!B5/'FS Data'!B40 -> 1.3809377 | C80: ='FS Data'!C5/'FS Data'!C40 -> 1.5026041 | D80: ='FS Data'!D5/'FS Data'!D40 -> 1.4807591 | E80: ='FS Data'!E5/'FS Data'!E40 -> 1.3602161 | F80: ='FS Data'!F5/'FS Data'!F40 -> 1.2507828 | G80: ='FS Data'!G5/'FS Data'!G40 -> 1.2545292
A81: Equity Multiplier (EM) = Total Assets / Equity | B81: ='FS Data'!B40/'FS Data'!B58 -> 1.8208352 | C81: ='FS Data'!C40/'FS Data'!C58 -> 1.8020639 | D81: ='FS Data'!D40/'FS Data'!D58 -> 1.6363886 | E81: ='FS Data'!E40/'FS Data'!E58 -> 1.6356967 | F81: ='FS Data'!F40/'FS Data'!F58 -> 2.2976438 | G81: ='FS Data'!G40/'FS Data'!G58 -> 2.1158498
A82: DuPont ROE = EB * IB * OPM * ATO * EM | B82: =B77*B78*B79*B80*B81 -> 0.52628716 | C82: =C77*C78*C79*C80*C81 -> 0.55738475 | D82: =D77*D78*D79*D80*D81 -> 0.45722579 | E82: =E77*E78*E79*E80*E81 -> 0.44880906 | F82: =F77*F78*F79*F80*F81 -> 0.25800492 | G82: =G77*G78*G79*G80*G81 -> 0.24047766
